src/__init__.py
src/__main__.py
src/_version.py
src/image.py
src/video.py
gemini_media_mcp-0.1.2.dist-info/METADATA
gemini_media_mcp-0.1.2.dist-info/WHEEL
gemini_media_mcp-0.1.2.dist-info/entry_points.txt
gemini_media_mcp-0.1.2.dist-info/licenses/LICENSE
gemini_media_mcp-0.1.2.dist-info/RECORD
