Metadata-Version: 2.4
Name: gemini-media-mcp
Version: 0.1.2
Summary: MCP server for Gemini media generation
Project-URL: Homepage, https://github.com/CxOAGI/gemini-media-mcp
Project-URL: Repository, https://github.com/CxOAGI/gemini-media-mcp
Project-URL: Issues, https://github.com/CxOAGI/gemini-media-mcp/issues
License:                                  Apache License
License-File: LICENSE
Requires-Python: >=3.13
Requires-Dist: aiohttp>=3.13.2
Requires-Dist: google-cloud-storage>=3.6.0
Requires-Dist: google-genai>=1.57.0
Requires-Dist: mcp>=1.23.1
Requires-Dist: pillow>=12.0.0
